vicedtools/__init__.py
vicedtools/educationperfect.py
vicedtools/sportstrak.py
vicedtools/acer/__init__.py
vicedtools/acer/ewritesittings.py
vicedtools/acer/extraoarsauthenticators.py
vicedtools/acer/oars.py
vicedtools/acer/oarsauthenticators.py
vicedtools/acer/oarscandidates.py
vicedtools/acer/oarssession.py
vicedtools/acer/oarstests.py
vicedtools/acer/patitems.py
vicedtools/acer/patresults.py
vicedtools/acer/patsittings.py
vicedtools/acer/plots.py
vicedtools/compass/__init__.py
vicedtools/compass/compassauthenticators.py
vicedtools/compass/compasssession.py
vicedtools/compass/extraauthenticators.py
vicedtools/compass/reports.py
vicedtools/dal/__init__.py
vicedtools/dal/utilities.py
vicedtools/gcp/__init__.py
vicedtools/gcp/api.py
vicedtools/gcp/format.py
vicedtools/gcp/schema.py
vicedtools/naplan/__init__.py
vicedtools/naplan/dataservicesession.py
vicedtools/naplan/reports.py
vicedtools/naplan/sssrdata.py
vicedtools/scripts/__init__.py
vicedtools/scripts/compassreportstobq.py
vicedtools/scripts/compassstudentdetailstobq.py
vicedtools/scripts/compassstudentenrolmenttobq.py
vicedtools/scripts/config.py
vicedtools/scripts/createcompassclassescsv.py
vicedtools/scripts/createcompassreportssummaries.py
vicedtools/scripts/createcompasssubjectsmetadatacsv.py
vicedtools/scripts/createnaplansummary.py
vicedtools/scripts/createoarsstudentimports.py
vicedtools/scripts/createpatparentlettertable.py
vicedtools/scripts/createsportstrakxlsx.py
vicedtools/scripts/createvcesummaries.py
vicedtools/scripts/ewritescorestobq.py
vicedtools/scripts/ewritesittingstoscores.py
vicedtools/scripts/exportcompassacademicgroups.py
vicedtools/scripts/exportcompassattendancehalfday.py
vicedtools/scripts/exportcompassclasses.py
vicedtools/scripts/exportcompassenrolments.py
vicedtools/scripts/exportcompasslearningtask.py
vicedtools/scripts/exportcompasslearningtasks.py
vicedtools/scripts/exportcompassprogressreport.py
vicedtools/scripts/exportcompassprogressreportcycles.py
vicedtools-0.0.10.1.dist-info/LICENSE
vicedtools-0.0.10.1.dist-info/METADATA
vicedtools-0.0.10.1.dist-info/WHEEL
vicedtools-0.0.10.1.dist-info/entry_points.txt
vicedtools-0.0.10.1.dist-info/top_level.txt
vicedtools-0.0.10.1.dist-info/RECORD
