Metadata-Version: 2.1
Name: vicedtools
Version: 0.0.10.1
Summary: A collection of tools for school data in Victorian schools.
Home-page: https://github.com/gregbreese/vicedtools
Author: Greg Breese
Project-URL: Bug Tracker, https://github.com/gregbreese/vicedtools/issues
Classifier: Programming Language :: Python :: 3
Classifier: License :: OSI Approved :: Apache Software License
Classifier: Operating System :: OS Independent
Classifier: Development Status :: 3 - Alpha
Requires-Python: >=3.8
License-File: LICENSE
Requires-Dist: browser-cookie3
Requires-Dist: bs4
Requires-Dist: cloudscraper
Requires-Dist: google-cloud-bigquery
Requires-Dist: google-cloud-storage
Requires-Dist: matplotlib
Requires-Dist: numpy
Requires-Dist: pandas
Requires-Dist: seaborn
Requires-Dist: selenium
Requires-Dist: seleniumbase
Requires-Dist: selenium-stealth
Requires-Dist: tomli
